Metadata-Version: 2.1
Name: cdep-all
Version: 0.0.6
Summary: Base package for the installation of the rest of icdep's dependencies
Home-page: UNKNOWN
Author: John Doe
Author-email: jmartinpe@sia.es
License: UNLICENSED
Platform: UNKNOWN
Classifier: Programming Language :: Python :: 3
Provides-Extra: subpackage_a
Provides-Extra: subpackage_b
